mangascraper
