Metadata-Version: 2.1
Name: MangaScraper
Version: 0.0.4
Summary: Web Scraper to find and read your favourite Mangas
Home-page: https://github.com/tanmyavishvakarma/MangaScraper
Author: Tanmya Vishvakarma)
Author-email: tanmya2000@gmail.com
License: MIT
Keywords: python,manga,scraper,mangascraper,anime,manga scraper
Platform: UNKNOWN
Classifier: License :: OSI Approved :: MIT License
Classifier: Development Status :: 1 - Planning
Classifier: Intended Audience :: Developers
Classifier: Programming Language :: Python :: 3
